fh_pydantic_form/__init__.py
fh_pydantic_form/color_utils.py
fh_pydantic_form/comparison_form.py
fh_pydantic_form/constants.py
fh_pydantic_form/defaults.py
fh_pydantic_form/field_renderers.py
fh_pydantic_form/form_parser.py
fh_pydantic_form/form_renderer.py
fh_pydantic_form/js_assets.py
fh_pydantic_form/list_path.py
fh_pydantic_form/py.typed
fh_pydantic_form/registry.py
fh_pydantic_form/type_helpers.py
fh_pydantic_form/ui_style.py
fh_pydantic_form/assets/__init__.py
fh_pydantic_form/assets/comparison-form.js
fh_pydantic_form/assets/form-renderer.js
fh_pydantic_form-0.3.18.dist-info/METADATA
fh_pydantic_form-0.3.18.dist-info/WHEEL
fh_pydantic_form-0.3.18.dist-info/licenses/LICENSE
fh_pydantic_form-0.3.18.dist-info/RECORD
