Metadata-Version: 2.4
Name: fh-pydantic-form
Version: 0.3.18
Summary: a library to turn any pydantic BaseModel object into a fasthtml/monsterui input form
Project-URL: Homepage, https://github.com/Marcura/fh-pydantic-form
Project-URL: Repository, https://github.com/Marcura/fh-pydantic-form
Project-URL: Documentation, https://github.com/Marcura/fh-pydantic-form
Author-email: Oege Dijk <o.dijk@marcura.com>
Maintainer-email: Oege Dijk <o.dijk@marcura.com>
License-File: LICENSE
Keywords: fasthtml,forms,monsterui,pydantic,ui,web
Classifier: License :: OSI Approved :: Apache Software License
Classifier: Operating System :: OS Independent
Classifier: Programming Language :: Python :: 3
Classifier: Programming Language :: Python :: 3.12
Classifier: Programming Language :: Python :: 3.13
Classifier: Programming Language :: Python :: 3.14
Classifier: Topic :: Internet :: WWW/HTTP :: Dynamic Content :: Content Management System
Classifier: Topic :: Software Development :: Libraries :: Python Modules
Requires-Python: >=3.12
Requires-Dist: monsterui>=1.0.29
Requires-Dist: pydantic>=2.0
Requires-Dist: python-fasthtml>=0.12.29
